README.md
setup.py
Anees/__init__.py
Anees/main.py
Anees.egg-info/PKG-INFO
Anees.egg-info/SOURCES.txt
Anees.egg-info/dependency_links.txt
Anees.egg-info/top_level.txt
test/__init__.py
test/test_main.py