Metadata-Version: 2.1
Name: Anees
Version: 0.1.0
Summary: Description of your package
Author: Anees afridi
Author-email: aneesafridi50@gmail.com
Classifier: Programming Language :: Python :: 3
